README.md
setup.py
nsqio/__init__.py
nsqio/utils.py
nsqio.egg-info/PKG-INFO
nsqio.egg-info/SOURCES.txt
nsqio.egg-info/dependency_links.txt
nsqio.egg-info/requires.txt
nsqio.egg-info/top_level.txt
nsqio/http/__init__.py
nsqio/http/base.py
nsqio/http/lookupd.py
nsqio/http/writer.py
nsqio/tcp/__init__.py
nsqio/tcp/connection.py
nsqio/tcp/consts.py
nsqio/tcp/exceptions.py
nsqio/tcp/messages.py
nsqio/tcp/protocol.py
nsqio/tcp/reader.py
nsqio/tcp/reader_rdy.py
nsqio/tcp/writer.py