Metadata-Version: 2.1
Name: nsqio
Version: 0.0.2
Summary: asyncio async/await nsq support
Home-page: https://github.com/rcrai/nsqio
Author: yuikns
Author-email: yuikns@users.noreply.github.com
License: MIT
Platform: POSIX
Classifier: License :: OSI Approved :: MIT License
Classifier: Development Status :: 3 - Alpha
Classifier: Programming Language :: Python
Classifier: Programming Language :: Python :: 3
Classifier: Programming Language :: Python :: 3.6
Classifier: Programming Language :: Python :: 3.7
Classifier: Programming Language :: Python :: 3.8
Classifier: Operating System :: POSIX
Classifier: Environment :: Web Environment
Classifier: Intended Audience :: Developers
Classifier: Topic :: Software Development
Classifier: Topic :: Software Development :: Libraries
